Postamt-0.1.0-py2.7-nspkg.pth
Postamt-0.1.0.dist-info/top_level.txt
Postamt-0.1.0.dist-info/entry_points.txt
Postamt-0.1.0.dist-info/METADATA
Postamt-0.1.0.dist-info/DESCRIPTION.rst
Postamt-0.1.0.dist-info/namespace_packages.txt
Postamt-0.1.0.dist-info/WHEEL
Postamt-0.1.0.dist-info/metadata.json
Postamt-0.1.0.dist-info/RECORD
postamt/model.py
postamt/scripts/admin.py
postamt/scripts/__init__.py
