Metadata-Version: 2.0
Name: Postamt
Version: 0.1.0
Summary: Maintain postamt sqlite db
Home-page: https://github.com/diefans/postamt-admin
Author: Oliver Berger
Author-email: diefans@gmail.com
License: Apache Version 2
Keywords: postfix dovecot sqlite
Platform: UNKNOWN
Classifier: Development Status :: 3 - Alpha
Classifier: Intended Audience :: Developers
Classifier: License :: OSI Approved :: Apache Software License
Classifier: Topic :: Communications :: Email
Classifier: Operating System :: OS Independent
Requires-Dist: sqlalchemy
Requires-Dist: click
